deskapp/__init__.py
deskapp/__main__.py
deskapp/mods/__init__.py
deskapp/mods/about.py
deskapp/mods/buttons.py
deskapp/mods/fire.py
deskapp/src/app.py
deskapp/src/backend.py
deskapp/src/callback.py
deskapp/src/cli.py
deskapp/src/frontend.py
deskapp/src/keys.py
deskapp/src/logic.py
deskapp/src/module.py
Deskapp-0.0.8.dist-info/LICENSE.txt
Deskapp-0.0.8.dist-info/METADATA
Deskapp-0.0.8.dist-info/WHEEL
Deskapp-0.0.8.dist-info/entry_points.txt
Deskapp-0.0.8.dist-info/top_level.txt
Deskapp-0.0.8.dist-info/RECORD
