Metadata-Version: 2.1
Name: Deskapp
Version: 0.0.8
Summary: An Open Source Terminal basesd Program Manager. Write and manage your own apps in this framework.
Home-page: https://ruckusist.com/deskapp
Author: Ruckusist
Author-email: ruckusist@outlook.com
Classifier: Development Status :: 4 - Beta
Classifier: Environment :: Console
Classifier: Intended Audience :: End Users/Desktop
Classifier: Intended Audience :: Developers
Classifier: Intended Audience :: System Administrators
Classifier: Operating System :: MacOS :: MacOS X
Classifier: Operating System :: POSIX
Classifier: Programming Language :: Python
Classifier: Topic :: Office/Business
License-File: LICENSE.txt
Requires-Dist: jinja2
